neonize-0.3.12.post1.dist-info/METADATA
neonize-0.3.12.post1.dist-info/WHEEL
neonize-0.3.12.post1.dist-info/entry_points.txt
neonize-0.3.12.post1.dist-info/licenses/LICENSE
neonize/__init__.py
neonize/_binder.py
neonize/aioze/__init__.py
neonize/aioze/client.py
neonize/aioze/events.py
neonize/aioze/preview/compose.py
neonize/aioze/preview/grabber.py
neonize/builder.py
neonize/client.py
neonize/const.py
neonize/download.py
neonize/events.py
neonize/exc.py
neonize/proto/Neonize_pb2.py
neonize/proto/Neonize_pb2.pyi
neonize/proto/__init__.py
neonize/proto/instamadilloAddMessage/InstamadilloAddMessage_pb2.py
neonize/proto/instamadilloAddMessage/InstamadilloAddMessage_pb2.pyi
neonize/proto/instamadilloCoreTypeActionLog/InstamadilloCoreTypeActionLog_pb2.py
neonize/proto/instamadilloCoreTypeActionLog/InstamadilloCoreTypeActionLog_pb2.pyi
neonize/proto/instamadilloCoreTypeAdminMessage/InstamadilloCoreTypeAdminMessage_pb2.py
neonize/proto/instamadilloCoreTypeAdminMessage/InstamadilloCoreTypeAdminMessage_pb2.pyi
neonize/proto/instamadilloCoreTypeCollection/InstamadilloCoreTypeCollection_pb2.py
neonize/proto/instamadilloCoreTypeCollection/InstamadilloCoreTypeCollection_pb2.pyi
neonize/proto/instamadilloCoreTypeLink/InstamadilloCoreTypeLink_pb2.py
neonize/proto/instamadilloCoreTypeLink/InstamadilloCoreTypeLink_pb2.pyi
neonize/proto/instamadilloCoreTypeMedia/InstamadilloCoreTypeMedia_pb2.py
neonize/proto/instamadilloCoreTypeMedia/InstamadilloCoreTypeMedia_pb2.pyi
neonize/proto/instamadilloCoreTypeText/InstamadilloCoreTypeText_pb2.py
neonize/proto/instamadilloCoreTypeText/InstamadilloCoreTypeText_pb2.pyi
neonize/proto/instamadilloDeleteMessage/InstamadilloDeleteMessage_pb2.py
neonize/proto/instamadilloDeleteMessage/InstamadilloDeleteMessage_pb2.pyi
neonize/proto/instamadilloSupplementMessage/InstamadilloSupplementMessage_pb2.py
neonize/proto/instamadilloSupplementMessage/InstamadilloSupplementMessage_pb2.pyi
neonize/proto/instamadilloTransportPayload/InstamadilloTransportPayload_pb2.py
neonize/proto/instamadilloTransportPayload/InstamadilloTransportPayload_pb2.pyi
neonize/proto/instamadilloXmaContentRef/InstamadilloXmaContentRef_pb2.py
neonize-0.3.12.post1.dist-info/RECORD
