Metadata-Version: 2.1
Name: neonize
Version: 0.3.12.post1
Summary: Neonize is a Python library designed to streamline the automation of tasks on WhatsApp
Project-URL: HomePage, https://github.com/krypton-byte/neonize
Requires-Python: >=3.10
Requires-Dist: httpx>=0.28.1
Requires-Dist: linkpreview>=0.11.0
Requires-Dist: phonenumbers>=8.13.52
Requires-Dist: pillow>=11.1.0
Requires-Dist: protobuf>=6.32.1
Requires-Dist: python-magic>=0.4.27; sys_platform != "win32"
Requires-Dist: python-magic-bin>=0.4.14; sys_platform == "win32"
Requires-Dist: requests>=2.32.3
Requires-Dist: segno>=1.6.1
Requires-Dist: tqdm>=4.67.1
